surveyReader.py
pysurveyreader-0.1.3.dist-info/METADATA
pysurveyreader-0.1.3.dist-info/WHEEL
pysurveyreader-0.1.3.dist-info/RECORD
