Metadata-Version: 2.4
Name: PySurveyReader
Version: 0.1.3
Summary: read qualtrics survey files via the qualtrics api and push them to snowflake!
Project-URL: Documentation, https://github.com/HughLong-code/PySurveyReader
Project-URL: Issues, https://github.com/HughLong-code/PySurveyReader/issues
Project-URL: Source, https://github.com/HughLong-code/PySurveyReader/tree/main/surveyReader
Author-email: Hugh Long <hal2209122@gmail.com>
License-Expression: MIT
Keywords: qualtrics,snowflake,survey
Classifier: Development Status :: 4 - Beta
Classifier: Programming Language :: Python
Classifier: Programming Language :: Python :: 3.8
Classifier: Programming Language :: Python :: 3.9
Classifier: Programming Language :: Python :: 3.10
Classifier: Programming Language :: Python :: 3.11
Classifier: Programming Language :: Python :: 3.12
Classifier: Programming Language :: Python :: Implementation :: CPython
Classifier: Programming Language :: Python :: Implementation :: PyPy
Requires-Python: >=3.8
Requires-Dist: pandas>=2.2.0
Requires-Dist: requests>=2.32.0
Requires-Dist: snowflake-connector-python>=3.14.1
Requires-Dist: snowflake-connector-python[pandas]
Requires-Dist: typing-extensions>=4.13.2
